opera_utils/__init__.py
opera_utils/_cslc.py
opera_utils/_dates.py
opera_utils/_helpers.py
opera_utils/_io.py
opera_utils/_types.py
opera_utils/_utils.py
opera_utils/_version.py
opera_utils/burst_frame_db.py
opera_utils/bursts.py
opera_utils/cli.py
opera_utils/constants.py
opera_utils/credentials.py
opera_utils/datasets.py
opera_utils/download.py
opera_utils/geometry.py
opera_utils/h5explorer.py
opera_utils/missing_data.py
opera_utils/py.typed
opera_utils/stitching.py
opera_utils/disp/__init__.py
opera_utils/disp/_download.py
opera_utils/disp/_enums.py
opera_utils/disp/_netcdf.py
opera_utils/disp/_product.py
opera_utils/disp/_rebase.py
opera_utils/disp/_reference.py
opera_utils/disp/_reformat.py
opera_utils/disp/_remote.py
opera_utils/disp/_search.py
opera_utils/disp/_utils.py
opera_utils/disp/create_incidence_range.py
opera_utils/disp/mintpy.py
opera_utils/disp/rebase_reference.py
opera_utils/tropo/__init__.py
opera_utils/tropo/_apply.py
opera_utils/tropo/_crop.py
opera_utils/tropo/_helpers.py
opera_utils-0.25.2.dist-info/licenses/LICENSE
opera_utils-0.25.2.dist-info/METADATA
opera_utils-0.25.2.dist-info/WHEEL
opera_utils-0.25.2.dist-info/entry_points.txt
opera_utils-0.25.2.dist-info/top_level.txt
opera_utils-0.25.2.dist-info/RECORD
