Metadata-Version: 2.4
Name: opera-utils
Version: 0.25.2
Summary: Miscellaneous utilities for working with OPERA data products
Author-email: Scott Staniewicz <scott.j.staniewicz@jpl.nasa.gov>
Project-URL: Homepage, https://github.com/opera-adt/opera-utils
Project-URL: Bug Tracker, https://github.com/opera-adt/opera-utils/issues
Project-URL: Discussions, https://github.com/opera-adt/opera-utils/discussions
Project-URL: Changelog, https://github.com/opera-adt/opera-utils/releases
Classifier: Intended Audience :: Developers
Classifier: Intended Audience :: Science/Research
Classifier: Programming Language :: Python :: 3
Classifier: Programming Language :: Python :: 3.9
Classifier: Programming Language :: Python :: 3.10
Classifier: Programming Language :: Python :: 3.11
Classifier: Programming Language :: Python :: 3.12
Classifier: Programming Language :: Python :: 3.13
Classifier: Programming Language :: Python
Classifier: Topic :: Scientific/Engineering
Classifier: Typing :: Typed
Requires-Python: >=3.9
License-File: LICENSE
Requires-Dist: h5py>=1.10
Requires-Dist: numpy>=1.24
Requires-Dist: pooch>=1.7
Requires-Dist: pyproj>=3.3
Requires-Dist: shapely>=1.8
Requires-Dist: typing_extensions>=4
Requires-Dist: tyro>=0.9
Provides-Extra: geopandas
Requires-Dist: geopandas; extra == "geopandas"
Requires-Dist: pyogrio; extra == "geopandas"
Provides-Extra: disp
Requires-Dist: affine; extra == "disp"
Requires-Dist: aiohttp; extra == "disp"
Requires-Dist: botocore; extra == "disp"
Requires-Dist: dask; extra == "disp"
Requires-Dist: fsspec; extra == "disp"
Requires-Dist: h5netcdf; extra == "disp"
Requires-Dist: s3fs; extra == "disp"
Requires-Dist: tqdm; extra == "disp"
Requires-Dist: rasterio; extra == "disp"
Requires-Dist: rioxarray; extra == "disp"
Requires-Dist: xarray; extra == "disp"
Requires-Dist: zarr>=3; extra == "disp"
Provides-Extra: tropo
Requires-Dist: opera-utils[disp]; extra == "tropo"
Requires-Dist: rioxarray; extra == "tropo"
Requires-Dist: scipy; extra == "tropo"
Provides-Extra: asf
Requires-Dist: asf_search; extra == "asf"
Provides-Extra: all
Requires-Dist: opera-utils[asf,disp,geopandas,tropo]; extra == "all"
Provides-Extra: test
Requires-Dist: asf_search; extra == "test"
Requires-Dist: pre-commit; extra == "test"
Requires-Dist: pytest; extra == "test"
Requires-Dist: pytest-cov; extra == "test"
Requires-Dist: pytest-randomly; extra == "test"
Requires-Dist: pytest-recording; extra == "test"
Requires-Dist: pytest-xdist; extra == "test"
Requires-Dist: ruff; extra == "test"
Requires-Dist: geopandas; extra == "test"
Requires-Dist: pyogrio; extra == "test"
Requires-Dist: ipywidgets; extra == "test"
Requires-Dist: matplotlib; extra == "test"
Provides-Extra: docs
Requires-Dist: mkdocs; extra == "docs"
Requires-Dist: mkdocs-gen-files; extra == "docs"
Requires-Dist: mkdocs-jupyter; extra == "docs"
Requires-Dist: mkdocs-literate-nav; extra == "docs"
Requires-Dist: mkdocs-material; extra == "docs"
Requires-Dist: mkdocs-section-index; extra == "docs"
Requires-Dist: mkdocstrings[python]; extra == "docs"
Requires-Dist: pybtex; extra == "docs"
Requires-Dist: pymdown-extensions; extra == "docs"
Dynamic: license-file
